keyring_wincred/__init__.py
keyring_wincred/powershell.py
keyring_wincred-0.1.0.dist-info/licenses/LICENSE
keyring_wincred-0.1.0.dist-info/METADATA
keyring_wincred-0.1.0.dist-info/WHEEL
keyring_wincred-0.1.0.dist-info/entry_points.txt
keyring_wincred-0.1.0.dist-info/top_level.txt
keyring_wincred-0.1.0.dist-info/RECORD
