Metadata-Version: 2.4
Name: keyring-wincred
Version: 0.1.0
Summary: Windows Credential Manager backend for keyring
Author-email: Andrea Scarpino <andrea@scarpino.dev>
License-Expression: MIT
Project-URL: Homepage, https://github.com/ilpianista/keyring_wincred
Classifier: Intended Audience :: Developers
Classifier: Operating System :: POSIX :: Linux
Classifier: Programming Language :: Python :: 3
Classifier: Programming Language :: Python :: 3.8
Classifier: Programming Language :: Python :: 3.9
Classifier: Programming Language :: Python :: 3.10
Classifier: Programming Language :: Python :: 3.11
Classifier: Programming Language :: Python :: 3.12
Requires-Python: >=3.8
License-File: LICENSE
Requires-Dist: keyring>=23.0.0
Requires-Dist: jaraco-classes>=3.2.3
Dynamic: license-file
